django_uzi/__init__.py
django_uzi/apps.py
django_uzi/core.py
django_uzi/settings.py
django_uzi-0.0.0.dist-info/LICENSE.txt
django_uzi-0.0.0.dist-info/WHEEL
django_uzi-0.0.0.dist-info/METADATA
django_uzi-0.0.0.dist-info/RECORD
